EasyML/__init__.py
EasyML/data.py
EasyML/evaluate.py
EasyML/model.py
EasyML/train.py
EasyML/utils.py
easyml_image-0.1.0.dist-info/licenses/LICENSE
easyml_image-0.1.0.dist-info/METADATA
easyml_image-0.1.0.dist-info/WHEEL
easyml_image-0.1.0.dist-info/top_level.txt
easyml_image-0.1.0.dist-info/RECORD
